[
  {
    "execution_id": "0000e1a7.6809aa54.01.01",
    "symbol": "MCL",
    "supports_tax_opt": "1",
    "side": "S",
    "order_description": "Sold 1 @ 61.62 on NYMEX",
    "trade_time": "20250424-10:32:21",
    "trade_time_r": 1745490741000,
    "size": 1.0,
    "price": "61.62",
    "exchange": "NYMEX",
    "commission": "0.77",
    "net_amount": 6162.0,
    "account": "DUE343675",
    "accountCode": "DUE343675",
    "account_allocation_name": "DUE343675",
    "company_name": "Micro WTI Crude Oil",
    "contract_description_1": "Aug'25",
    "sec_type": "FUT",
    "listing_exchange": "NYMEX",
    "conid": 661016511,
    "conidEx": "661016511@NYMEX",
    "clearing_id": "IB",
    "clearing_name": "IB",
    "liquidation_trade": "0",
    "is_event_trading": "0"
  },
  {
    "execution_id": "0000e1a7.6809a6e0.01.01",
    "symbol": "ZW",
    "supports_tax_opt": "1",
    "side": "B",
    "order_description": "Bot 1 @ 541 3/4 on CBOT",
    "trade_time": "20250424-09:57:31",
    "trade_time_r": 1745488651000,
    "size": 1.0,
    "price": "541 3/4",
    "exchange": "CBOT",
    "commission": "3.0",
    "net_amount": 27087.5,
    "account": "DUE343675",
    "accountCode": "DUE343675",
    "account_allocation_name": "DUE343675",
    "company_name": "Wheat Futures",
    "contract_description_1": "Jul14 '25",
    "sec_type": "FUT",
    "listing_exchange": "CBOT",
    "conid": 573366622,
    "conidEx": "573366622@CBOT",
    "clearing_id": "IB",
    "clearing_name": "IB",
    "liquidation_trade": "0",
    "is_event_trading": "0"
  },
  {
    "execution_id": "0000e1a7.6809ec2c.01.01",
    "symbol": "ZS",
    "supports_tax_opt": "1",
    "side": "S",
    "order_description": "Sold 1 @ 1052 3/4 on CBOT",
    "trade_time": "20250424-14:41:43",
    "trade_time_r": 1745505703000,
    "size": 1.0,
    "price": "1052 3/4",
    "exchange": "CBOT",
    "commission": "3.0",
    "net_amount": 52637.5,
    "account": "DUE343675",
    "accountCode": "DUE343675",
    "account_allocation_name": "DUE343675",
    "company_name": "Soybean Futures",
    "contract_description_1": "Jul14 '25",
    "sec_type": "FUT",
    "listing_exchange": "CBOT",
    "conid": 526262961,
    "conidEx": "526262961@CBOT",
    "clearing_id": "IB",
    "clearing_name": "IB",
    "liquidation_trade": "0",
    "is_event_trading": "0"
  },
  {
    "execution_id": "0000e1a7.6809ab6d.01.01",
    "symbol": "MES",
    "supports_tax_opt": "1",
    "side": "B",
    "order_description": "Bot 1 @ 5438.25 on CME",
    "trade_time": "20250424-10:44:47",
    "trade_time_r": 1745491487000,
    "size": 1.0,
    "price": "5438.25",
    "exchange": "CME",
    "commission": "0.62",
    "net_amount": 27191.25,
    "account": "DUE343675",
    "accountCode": "DUE343675",
    "account_allocation_name": "DUE343675",
    "company_name": "Micro E-Mini S&P 500 Stock Price Index",
    "contract_description_1": "Sep19 '25",
    "sec_type": "FUT",
    "listing_exchange": "CME",
    "conid": 711280067,
    "conidEx": "711280067@CME",
    "clearing_id": "IB",
    "clearing_name": "IB",
    "liquidation_trade": "0",
    "is_event_trading": "0"
  },
  {
    "execution_id": "0000e1a7.6809ae95.01.01",
    "symbol": "ZL",
    "supports_tax_opt": "1",
    "side": "B",
    "order_description": "Bot 2 @ 48.75 on CBOT",
    "trade_time": "20250424-11:06:07",
    "trade_time_r": 1745492767000,
    "size": 2.0,
    "price": "48.75",
    "exchange": "CBOT",
    "commission": "6.0",
    "net_amount": 58500.0,
    "account": "DUE343675",
    "accountCode": "DUE343675",
    "account_allocation_name": "DUE343675",
    "company_name": "Soybean Oil Futures",
    "contract_description_1": "Jul14 '25",
    "sec_type": "FUT",
    "listing_exchange": "CBOT",
    "conid": 532513438,
    "conidEx": "532513438@CBOT",
    "clearing_id": "IB",
    "clearing_name": "IB",
    "liquidation_trade": "0",
    "is_event_trading": "0"
  },
  {
    "execution_id": "0000e1a7.6809d9ee.01.01",
    "symbol": "ZC",
    "supports_tax_opt": "1",
    "side": "B",
    "order_description": "Bot 2 @ 481 3/4 on CBOT",
    "trade_time": "20250424-14:04:23",
    "trade_time_r": 1745503463000,
    "size": 2.0,
    "price": "481 3/4",
    "exchange": "CBOT",
    "commission": "6.0",
    "net_amount": 48175.0,
    "account": "DUE343675",
    "accountCode": "DUE343675",
    "account_allocation_name": "DUE343675",
    "company_name": "Corn Futures",
    "contract_description_1": "Jul14 '25",
    "sec_type": "FUT",
    "listing_exchange": "CBOT",
    "conid": 532513377,
    "conidEx": "532513377@CBOT",
    "clearing_id": "IB",
    "clearing_name": "IB",
    "liquidation_trade": "0",
    "is_event_trading": "0"
  },
  {
    "execution_id": "0000e1a7.6809d191.01.01",
    "symbol": "ZL",
    "supports_tax_opt": "1",
    "side": "S",
    "order_description": "Sold 2 @ 48.63 on CBOT",
    "trade_time": "20250424-13:46:46",
    "trade_time_r": 1745502406000,
    "size": 2.0,
    "price": "48.63",
    "exchange": "CBOT",
    "commission": "6.0",
    "net_amount": 58356.0,
    "account": "DUE343675",
    "accountCode": "DUE343675",
    "account_allocation_name": "DUE343675",
    "company_name": "Soybean Oil Futures",
    "contract_description_1": "Jul14 '25",
    "sec_type": "FUT",
    "listing_exchange": "CBOT",
    "conid": 532513438,
    "conidEx": "532513438@CBOT",
    "clearing_id": "IB",
    "clearing_name": "IB",
    "liquidation_trade": "0",
    "is_event_trading": "0"
  },
  {
    "execution_id": "0000e1a7.6809f1cd.01.01",
    "symbol": "ZS",
    "supports_tax_opt": "1",
    "side": "B",
    "order_description": "Bot 2 @ 1053 1/2 on CBOT",
    "trade_time": "20250424-14:52:37",
    "trade_time_r": 1745506357000,
    "size": 2.0,
    "price": "1053 1/2",
    "exchange": "CBOT",
    "commission": "6.0",
    "net_amount": 105350.0,
    "account": "DUE343675",
    "accountCode": "DUE343675",
    "account_allocation_name": "DUE343675",
    "company_name": "Soybean Futures",
    "contract_description_1": "Jul14 '25",
    "sec_type": "FUT",
    "listing_exchange": "CBOT",
    "conid": 526262961,
    "conidEx": "526262961@CBOT",
    "clearing_id": "IB",
    "clearing_name": "IB",
    "liquidation_trade": "0",
    "is_event_trading": "0"
  },
  {
    "execution_id": "0000e1a7.6809b7c8.01.01",
    "symbol": "SB",
    "supports_tax_opt": "1",
    "side": "B",
    "order_description": "Bot 1 @ 17.92 on NYBOT",
    "trade_time": "20250424-12:18:13",
    "trade_time_r": 1745497093000,
    "size": 1.0,
    "price": "17.92",
    "exchange": "NYBOT",
    "commission": "2.97",
    "net_amount": 20070.4,
    "account": "DUE343675",
    "accountCode": "DUE343675",
    "account_allocation_name": "DUE343675",
    "company_name": "Sugar No. 11",
    "contract_description_1": "Jul'25",
    "sec_type": "FUT",
    "listing_exchange": "NYBOT",
    "conid": 577421489,
    "conidEx": "577421489@NYBOT",
    "clearing_id": "IB",
    "clearing_name": "IB",
    "liquidation_trade": "0",
    "is_event_trading": "0"
  },
  {
    "execution_id": "0000e1a7.6809effa.01.01",
    "symbol": "SB",
    "supports_tax_opt": "1",
    "side": "S",
    "order_description": "Sold 1 @ 17.74 on NYBOT",
    "trade_time": "20250424-14:48:50",
    "trade_time_r": 1745506130000,
    "size": 1.0,
    "price": "17.74",
    "exchange": "NYBOT",
    "commission": "2.97",
    "net_amount": 19868.8,
    "account": "DUE343675",
    "accountCode": "DUE343675",
    "account_allocation_name": "DUE343675",
    "company_name": "Sugar No. 11",
    "contract_description_1": "Jul'25",
    "sec_type": "FUT",
    "listing_exchange": "NYBOT",
    "conid": 577421489,
    "conidEx": "577421489@NYBOT",
    "clearing_id": "IB",
    "clearing_name": "IB",
    "liquidation_trade": "0",
    "is_event_trading": "0"
  },
  {
    "execution_id": "0000e1a7.6809bf37.01.01",
    "symbol": "MHG",
    "supports_tax_opt": "1",
    "side": "S",
    "order_description": "Sold 2 @ 4.9025 on COMEX",
    "trade_time": "20250424-12:52:21",
    "trade_time_r": 1745499141000,
    "size": 2.0,
    "price": "4.9025",
    "exchange": "COMEX",
    "commission": "1.74",
    "net_amount": 24512.5,
    "account": "DUE343675",
    "accountCode": "DUE343675",
    "account_allocation_name": "DUE343675",
    "company_name": "Micro Copper",
    "contract_description_1": "Jul'25",
    "sec_type": "FUT",
    "listing_exchange": "COMEX",
    "conid": 559306286,
    "conidEx": "559306286@COMEX",
    "clearing_id": "IB",
    "clearing_name": "IB",
    "liquidation_trade": "0",
    "is_event_trading": "0"
  },
  {
    "execution_id": "0000e1a7.6809ab6f.01.01",
    "symbol": "MYM",
    "supports_tax_opt": "1",
    "side": "B",
    "order_description": "Bot 1 @ 39917 on CBOT",
    "trade_time": "20250424-10:44:47",
    "trade_time_r": 1745491487000,
    "size": 1.0,
    "price": "39917",
    "exchange": "CBOT",
    "commission": "0.62",
    "net_amount": 19958.5,
    "account": "DUE343675",
    "accountCode": "DUE343675",
    "account_allocation_name": "DUE343675",
    "company_name": "Micro E-Mini Dow Jones Industrial Average Index",
    "contract_description_1": "Sep19 '25",
    "sec_type": "FUT",
    "listing_exchange": "CBOT",
    "conid": 730283051,
    "conidEx": "730283051@CBOT",
    "clearing_id": "IB",
    "clearing_name": "IB",
    "liquidation_trade": "0",
    "is_event_trading": "0"
  },
  {
    "execution_id": "0000e1a7.6809a0f7.01.01",
    "symbol": "MCL",
    "supports_tax_opt": "1",
    "side": "S",
    "order_description": "Sold 1 @ 61.36 on NYMEX",
    "trade_time": "20250424-08:52:47",
    "trade_time_r": 1745484767000,
    "size": 1.0,
    "price": "61.36",
    "exchange": "NYMEX",
    "commission": "0.77",
    "net_amount": 6136.0,
    "account": "DUE343675",
    "accountCode": "DUE343675",
    "account_allocation_name": "DUE343675",
    "company_name": "Micro WTI Crude Oil",
    "contract_description_1": "Aug'25",
    "sec_type": "FUT",
    "listing_exchange": "NYMEX",
    "conid": 661016511,
    "conidEx": "661016511@NYMEX",
    "clearing_id": "IB",
    "clearing_name": "IB",
    "liquidation_trade": "0",
    "is_event_trading": "0"
  },
  {
    "execution_id": "0000e1a7.680a25c0.01.01",
    "symbol": "MHG",
    "supports_tax_opt": "1",
    "side": "B",
    "order_description": "Bot 2 @ 4.9220 on COMEX",
    "trade_time": "20250424-17:28:03",
    "trade_time_r": 1745515683000,
    "size": 2.0,
    "price": "4.9220",
    "exchange": "COMEX",
    "commission": "1.74",
    "net_amount": 24610.0,
    "account": "DUE343675",
    "accountCode": "DUE343675",
    "account_allocation_name": "DUE343675",
    "company_name": "Micro Copper",
    "contract_description_1": "Jul'25",
    "sec_type": "FUT",
    "listing_exchange": "COMEX",
    "conid": 559306286,
    "conidEx": "559306286@COMEX",
    "clearing_id": "IB",
    "clearing_name": "IB",
    "liquidation_trade": "0",
    "is_event_trading": "0"
  },
  {
    "execution_id": "0000e1a7.68099249.01.01",
    "symbol": "MHG",
    "supports_tax_opt": "1",
    "side": "B",
    "order_description": "Bot 1 @ 4.9000 on COMEX",
    "trade_time": "20250424-07:00:20",
    "trade_time_r": 1745478020000,
    "size": 1.0,
    "price": "4.9000",
    "exchange": "COMEX",
    "commission": "0.87",
    "net_amount": 12250.0,
    "account": "DUE343675",
    "accountCode": "DUE343675",
    "account_allocation_name": "DUE343675",
    "company_name": "Micro Copper",
    "contract_description_1": "Jul'25",
    "sec_type": "FUT",
    "listing_exchange": "COMEX",
    "conid": 559306286,
    "conidEx": "559306286@COMEX",
    "clearing_id": "IB",
    "clearing_name": "IB",
    "liquidation_trade": "0",
    "is_event_trading": "0"
  },
  {
    "execution_id": "0000e1a7.6809eff9.01.01",
    "symbol": "SB",
    "supports_tax_opt": "1",
    "side": "S",
    "order_description": "Sold 1 @ 17.74 on NYBOT",
    "trade_time": "20250424-14:48:50",
    "trade_time_r": 1745506130000,
    "size": 1.0,
    "price": "17.74",
    "exchange": "NYBOT",
    "commission": "2.97",
    "net_amount": 19868.8,
    "account": "DUE343675",
    "accountCode": "DUE343675",
    "account_allocation_name": "DUE343675",
    "company_name": "Sugar No. 11",
    "contract_description_1": "Jul'25",
    "sec_type": "FUT",
    "listing_exchange": "NYBOT",
    "conid": 577421489,
    "conidEx": "577421489@NYBOT",
    "clearing_id": "IB",
    "clearing_name": "IB",
    "liquidation_trade": "0",
    "is_event_trading": "0"
  },
  {
    "execution_id": "0000e1a7.6809f1b6.01.01",
    "symbol": "ZL",
    "supports_tax_opt": "1",
    "side": "B",
    "order_description": "Bot 1 @ 49.00 on CBOT",
    "trade_time": "20250424-14:52:19",
    "trade_time_r": 1745506339000,
    "size": 1.0,
    "price": "49.00",
    "exchange": "CBOT",
    "commission": "3.0",
    "net_amount": 29400.0,
    "account": "DUE343675",
    "accountCode": "DUE343675",
    "account_allocation_name": "DUE343675",
    "company_name": "Soybean Oil Futures",
    "contract_description_1": "Jul14 '25",
    "sec_type": "FUT",
    "listing_exchange": "CBOT",
    "conid": 532513438,
    "conidEx": "532513438@CBOT",
    "clearing_id": "IB",
    "clearing_name": "IB",
    "liquidation_trade": "0",
    "is_event_trading": "0"
  },
  {
    "execution_id": "0000e1a7.6809c6ad.01.01",
    "symbol": "ZW",
    "supports_tax_opt": "1",
    "side": "S",
    "order_description": "Sold 2 @ 541 1/2 on CBOT",
    "trade_time": "20250424-13:30:53",
    "trade_time_r": 1745501453000,
    "size": 2.0,
    "price": "541 1/2",
    "exchange": "CBOT",
    "commission": "6.0",
    "net_amount": 54150.0,
    "account": "DUE343675",
    "accountCode": "DUE343675",
    "account_allocation_name": "DUE343675",
    "company_name": "Wheat Futures",
    "contract_description_1": "Jul14 '25",
    "sec_type": "FUT",
    "listing_exchange": "CBOT",
    "conid": 573366622,
    "conidEx": "573366622@CBOT",
    "clearing_id": "IB",
    "clearing_name": "IB",
    "liquidation_trade": "0",
    "is_event_trading": "0"
  },
  {
    "execution_id": "0000e1a7.6809f1b8.01.01",
    "symbol": "ZL",
    "supports_tax_opt": "1",
    "side": "B",
    "order_description": "Bot 1 @ 49.00 on CBOT",
    "trade_time": "20250424-14:52:20",
    "trade_time_r": 1745506340000,
    "size": 1.0,
    "price": "49.00",
    "exchange": "CBOT",
    "commission": "3.0",
    "net_amount": 29400.0,
    "account": "DUE343675",
    "accountCode": "DUE343675",
    "account_allocation_name": "DUE343675",
    "company_name": "Soybean Oil Futures",
    "contract_description_1": "Jul14 '25",
    "sec_type": "FUT",
    "listing_exchange": "CBOT",
    "conid": 532513438,
    "conidEx": "532513438@CBOT",
    "clearing_id": "IB",
    "clearing_name": "IB",
    "liquidation_trade": "0",
    "is_event_trading": "0"
  },
  {
    "execution_id": "0000e1a7.6809b401.01.01",
    "symbol": "ZS",
    "supports_tax_opt": "1",
    "side": "S",
    "order_description": "Sold 1 @ 1054 1/2 on CBOT",
    "trade_time": "20250424-11:49:06",
    "trade_time_r": 1745495346000,
    "size": 1.0,
    "price": "1054 1/2",
    "exchange": "CBOT",
    "commission": "3.0",
    "net_amount": 52725.0,
    "account": "DUE343675",
    "accountCode": "DUE343675",
    "account_allocation_name": "DUE343675",
    "company_name": "Soybean Futures",
    "contract_description_1": "Jul14 '25",
    "sec_type": "FUT",
    "listing_exchange": "CBOT",
    "conid": 526262961,
    "conidEx": "526262961@CBOT",
    "clearing_id": "IB",
    "clearing_name": "IB",
    "liquidation_trade": "0",
    "is_event_trading": "0"
  },
  {
    "execution_id": "0000e1a7.68099f77.01.01",
    "symbol": "ZL",
    "supports_tax_opt": "1",
    "side": "S",
    "order_description": "Sold 2 @ 48.55 on CBOT",
    "trade_time": "20250424-08:40:20",
    "trade_time_r": 1745484020000,
    "size": 2.0,
    "price": "48.55",
    "exchange": "CBOT",
    "commission": "6.0",
    "net_amount": 58260.0,
    "account": "DUE343675",
    "accountCode": "DUE343675",
    "account_allocation_name": "DUE343675",
    "company_name": "Soybean Oil Futures",
    "contract_description_1": "Jul14 '25",
    "sec_type": "FUT",
    "listing_exchange": "CBOT",
    "conid": 532513438,
    "conidEx": "532513438@CBOT",
    "clearing_id": "IB",
    "clearing_name": "IB",
    "liquidation_trade": "0",
    "is_event_trading": "0"
  },
  {
    "execution_id": "0000e1a7.6809f467.01.01",
    "symbol": "ZS",
    "supports_tax_opt": "1",
    "side": "B",
    "order_description": "Bot 1 @ 1053 1/2 on CBOT",
    "trade_time": "20250424-15:01:23",
    "trade_time_r": 1745506883000,
    "size": 1.0,
    "price": "1053 1/2",
    "exchange": "CBOT",
    "commission": "3.0",
    "net_amount": 52675.0,
    "account": "DUE343675",
    "accountCode": "DUE343675",
    "account_allocation_name": "DUE343675",
    "company_name": "Soybean Futures",
    "contract_description_1": "Jul14 '25",
    "sec_type": "FUT",
    "listing_exchange": "CBOT",
    "conid": 526262961,
    "conidEx": "526262961@CBOT",
    "clearing_id": "IB",
    "clearing_name": "IB",
    "liquidation_trade": "0",
    "is_event_trading": "0"
  },
  {
    "execution_id": "0000e1a7.680a29f0.01.01",
    "symbol": "ZW",
    "supports_tax_opt": "1",
    "side": "B",
    "order_description": "Bot 2 @ 544 1/4 on CBOT",
    "trade_time": "20250424-17:41:52",
    "trade_time_r": 1745516512000,
    "size": 2.0,
    "price": "544 1/4",
    "exchange": "CBOT",
    "commission": "6.0",
    "net_amount": 54425.0,
    "account": "DUE343675",
    "accountCode": "DUE343675",
    "account_allocation_name": "DUE343675",
    "company_name": "Wheat Futures",
    "contract_description_1": "Jul14 '25",
    "sec_type": "FUT",
    "listing_exchange": "CBOT",
    "conid": 573366622,
    "conidEx": "573366622@CBOT",
    "clearing_id": "IB",
    "clearing_name": "IB",
    "liquidation_trade": "0",
    "is_event_trading": "0"
  },
  {
    "execution_id": "0000e1a7.6809b3a0.01.01",
    "symbol": "ZC",
    "supports_tax_opt": "1",
    "side": "S",
    "order_description": "Sold 1 @ 480 1/4 on CBOT",
    "trade_time": "20250424-11:44:52",
    "trade_time_r": 1745495092000,
    "size": 1.0,
    "price": "480 1/4",
    "exchange": "CBOT",
    "commission": "3.0",
    "net_amount": 24012.5,
    "account": "DUE343675",
    "accountCode": "DUE343675",
    "account_allocation_name": "DUE343675",
    "company_name": "Corn Futures",
    "contract_description_1": "Jul14 '25",
    "sec_type": "FUT",
    "listing_exchange": "CBOT",
    "conid": 532513377,
    "conidEx": "532513377@CBOT",
    "clearing_id": "IB",
    "clearing_name": "IB",
    "liquidation_trade": "0",
    "is_event_trading": "0"
  }
]